{
	"archive" : {},
	"artifacts" : 
	[
		{
			"path" : "ext/glad/libglad.a"
		}
	],
	"backtrace" : 1,
	"backtraceGraph" : 
	{
		"commands" : 
		[
			"add_library",
			"target_include_directories"
		],
		"files" : 
		[
			"ext/glad/CMakeLists.txt"
		],
		"nodes" : 
		[
			{
				"file" : 0
			},
			{
				"command" : 0,
				"file" : 0,
				"line" : 5,
				"parent" : 0
			},
			{
				"command" : 1,
				"file" : 0,
				"line" : 11,
				"parent" : 0
			}
		]
	},
	"compileGroups" : 
	[
		{
			"compileCommandFragments" : 
			[
				{
					"fragment" : " -isysroot /Library/Developer/CommandLineTools/SDKs/MacOSX10.15.sdk"
				}
			],
			"includes" : 
			[
				{
					"backtrace" : 2,
					"path" : "/Users/fenglongsong/Documents/GitHub/a2-FenglongSong/ext/glad/include"
				}
			],
			"language" : "C",
			"sourceIndexes" : 
			[
				2
			]
		}
	],
	"id" : "glad::@395c76cf0743a1c2a345",
	"name" : "glad",
	"nameOnDisk" : "libglad.a",
	"paths" : 
	{
		"build" : "ext/glad",
		"source" : "ext/glad"
	},
	"sourceGroups" : 
	[
		{
			"name" : "Header Files",
			"sourceIndexes" : 
			[
				0,
				1
			]
		},
		{
			"name" : "Source Files",
			"sourceIndexes" : 
			[
				2
			]
		}
	],
	"sources" : 
	[
		{
			"backtrace" : 1,
			"path" : "ext/glad/include/glad/glad.h",
			"sourceGroupIndex" : 0
		},
		{
			"backtrace" : 1,
			"path" : "ext/glad/include/KHR/khrplatform.h",
			"sourceGroupIndex" : 0
		},
		{
			"backtrace" : 1,
			"compileGroupIndex" : 0,
			"path" : "ext/glad/src/glad.c",
			"sourceGroupIndex" : 1
		}
	],
	"type" : "STATIC_LIBRARY"
}
